ictmpl/__init__.py
ictmpl/__version__.py
ictmpl/app.py
ictmpl/argparser.py
ictmpl/config.py
ictmpl/dependency.py
ictmpl/ictmpl.py
ictmpl/param.py
ictmpl/helpers/__init__.py
ictmpl/helpers/fsutil.py
ictmpl/helpers/git.py
ictmpl/methods/__init__.py
ictmpl/methods/create.py
ictmpl-1.2.0.dist-info/METADATA
ictmpl-1.2.0.dist-info/RECORD
ictmpl-1.2.0.dist-info/WHEEL
ictmpl-1.2.0.dist-info/entry_points.txt
ictmpl-1.2.0.dist-info/top_level.txt
