Metadata-Version: 2.1
Name: ictmpl
Version: 1.2.0
Summary: Generate projects from templates
Home-page: https://github.com/ideascup/ictmpl/
Author: Dmitriy Pleshevskiy
Author-email: dmitriy@ideascup.me
License: MIT
Platform: UNKNOWN
